LICENSE
MANIFEST.in
README.rst
setup.py
hdlparse/__init__.py
hdlparse/minilexer.py
hdlparse/verilog_parser.py
hdlparse/vhdl_parser.py
hdlparse.egg-info/PKG-INFO
hdlparse.egg-info/SOURCES.txt
hdlparse.egg-info/dependency_links.txt
hdlparse.egg-info/top_level.txt