Metadata-Version: 1.1
Name: hdlparse
Version: 1.0.1
Summary: HDL parser
Home-page: http://kevinpt.github.io/hdlparse
Author: Kevin Thibedeau
Author-email: kevin.thibedeau@gmail.com
License: MIT
Download-URL: http://kevinpt.github.io/hdlparse
Keywords: HDL parser
Platform: Any
Classifier: Development Status :: 5 - Production/Stable
Classifier: Operating System :: OS Independent
Classifier: Intended Audience :: Developers
Classifier: Topic :: Text Processing :: General
Classifier: Natural Language :: English
Classifier: Programming Language :: Python :: 2.7
Classifier: Programming Language :: Python :: 3
Classifier: License :: OSI Approved :: MIT License
